qkd_simulator/__init__.py
qkd_simulator/backend.py
qkd_simulator/configuration.py
qkd_simulator/database.py
qkd_simulator/grpc_serialization/__init__.py
qkd_simulator/grpc_serialization/interfaces_pb2.py
qkd_simulator/grpc_serialization/interfaces_pb2_grpc.py
qkd_simulator/key_management.py
qkd_simulator/key_synchronization.py
qkd_simulator/main.py
qkd_simulator/protobufs/interfaces.proto
qkd_simulator-0.1.4.dist-info/METADATA
qkd_simulator-0.1.4.dist-info/WHEEL
qkd_simulator-0.1.4.dist-info/entry_points.txt
qkd_simulator-0.1.4.dist-info/RECORD
