Metadata-Version: 2.1
Name: qkd_simulator
Version: 0.1.4
Summary: 
Author: rmcelaya
Author-email: rmcelaya@protonmail.com
Requires-Python: >=3.6,<4.0
Classifier: Programming Language :: Python :: 3
Classifier: Programming Language :: Python :: 3.6
Classifier: Programming Language :: Python :: 3.7
Classifier: Programming Language :: Python :: 3.8
Classifier: Programming Language :: Python :: 3.9
Classifier: Programming Language :: Python :: 3.10
Classifier: Programming Language :: Python :: 3.11
Requires-Dist: aioconsole (==0.3.3)
Requires-Dist: bitarray (==2.8.1)
Requires-Dist: grpcio (==1.48.2)
Requires-Dist: pickle-mixin (==1.0.2)
Requires-Dist: protobuf (==3.19.6)
Requires-Dist: simulaqron (==3.0.16)
